stratage/__init__.py
stratage/geochron.py
stratage/stratage.py
stratage-1.1.0.dist-info/licenses/LICENSE.txt
stratage-1.1.0.dist-info/METADATA
stratage-1.1.0.dist-info/WHEEL
stratage-1.1.0.dist-info/top_level.txt
stratage-1.1.0.dist-info/RECORD
