Metadata-Version: 2.4
Name: StratAge
Version: 1.1.0
Summary: Bayesian age modeling of stratigraphy.
Home-page: https://github.com/sarttiso/stratage
Author: Adrian Tasistro-Hart
Author-email: adrian@tasistro-hart.com
License: GPL-3.0-only
Project-URL: Documentation, https://adrian.tasistro-hart.com/stratage/index.html
Project-URL: Source, https://github.com/sarttiso/stratage
Project-URL: Changelog, https://adrian.tasistro-hart.com/stratage/changelog.html
Platform: any
Classifier: Development Status :: 5 - Production/Stable
Classifier: Programming Language :: Python
License-File: LICENSE.txt
Requires-Dist: importlib-metadata; python_version < "3.8"
Requires-Dist: numba
Requires-Dist: numpy
Requires-Dist: pymc
Requires-Dist: scipy
Requires-Dist: tqdm
Requires-Dist: matplotlib
Requires-Dist: joblib
Provides-Extra: testing
Requires-Dist: setuptools; extra == "testing"
Requires-Dist: pytest; extra == "testing"
Requires-Dist: pytest-cov; extra == "testing"
Dynamic: license-file
